tests/test_template_utils.py
tests/test_template_utils_split_words.py
wukong/__init__.py
wukong/cli.py
wukong/code_review.py
wukong/coder.py
wukong/coding_assistant.py
wukong/llmclient.py
wukong/project_create.py
wukong/project_init.py
wukong/shell.py
wukong/source_code_utils.py
wukong/version.py
wukong/wukong_config.py
wukong/agents/file_mcp_client.py
wukong/agents/file_mcp_server.py
wukong/commands/__init__.py
wukong/commands/cli_utils.py
wukong/commands/fastapi_project_init.py
wukong/commands/flask_codegen.py
wukong/commands/flask_crud.py
wukong/commands/flask_project_init.py
wukong/commands/jinja2_template_render.py
wukong/commands/rdb_metadata_extractor.py
wukong/commands/setup_database.py
wukong/commands/template_utils.py
wukong/commands/vue_project_init.py
wukong/commands/wukong_env.py
wukong/commands/samples/__init__.py
wukong/commands/samples/app.py.txt
wukong/commands/samples/commands.py.txt
wukong/commands/samples/errors.py.txt
wukong/commands/samples/extensions.py.txt
wukong/commands/samples/flask_config.py.txt
wukong/commands/samples/flaskenv.txt
wukong/commands/samples/gitignore.txt
wukong/commands/samples/helpers.py.txt
wukong/commands/samples/model_base.py.txt
wukong/commands/samples/pytest.ini
wukong/commands/samples/requirements.txt
wukong/commands/samples/router.py.txt
wukong/commands/samples/wsgi.py.txt
wukong/commands/templates/backend/Dockerfile.j2
wukong/commands/templates/backend/api_resource.py.j2
wukong/commands/templates/backend/config.py.j2
wukong/commands/templates/backend/crud.py.j2
wukong/commands/templates/backend/dao.py.j2
wukong/commands/templates/backend/database.py.j2
wukong/commands/templates/backend/main.py.j2
wukong/commands/templates/backend/model.py.j2
wukong/commands/templates/backend/pytest.ini.j2
wukong/commands/templates/backend/readme.md.j2
wukong/commands/templates/backend/requirements.txt.j2
wukong/commands/templates/backend/router.py.j2
wukong/commands/templates/backend/schema.py.j2
wukong_stack-0.1.4.dist-info/licenses/LICENSE
wukong_stack-0.1.4.dist-info/METADATA
wukong_stack-0.1.4.dist-info/WHEEL
wukong_stack-0.1.4.dist-info/entry_points.txt
wukong_stack-0.1.4.dist-info/top_level.txt
wukong_stack-0.1.4.dist-info/RECORD
