Metadata-Version: 2.4
Name: wukong-stack
Version: 0.1.4
Summary: WukongStack is a dynamic CLI tool that generates a full-stack web application skeleton
Home-page: https://github.com/devsunny/wukong-stack
Author: Sunny Liu
Author-email: Sunny Liu <sunnyliu2@gmail.com>
License: MIT
Project-URL: Homepage, https://github.com/devsunny/wukong-stack
Project-URL: Documentation, https://github.com/devsunny/wukong-stack/README.md
Project-URL: Repository, https://github.com/devsunny/wukong-stack
Classifier: Development Status :: 4 - Beta
Classifier: Intended Audience :: Developers
Classifier: License :: OSI Approved :: MIT License
Classifier: Programming Language :: Python :: 3
Classifier: Programming Language :: Python :: 3.10
Classifier: Programming Language :: Python :: 3.11
Classifier: Programming Language :: Python :: 3.12
Classifier: Programming Language :: Python :: 3.13
Classifier: Programming Language :: Python :: 3.14
Classifier: Topic :: Utilities
Requires-Python: >=3.7
License-File: LICENSE
Requires-Dist: fastapi==0.116.1
Requires-Dist: uvicorn==0.35.0
Requires-Dist: sqlalchemy==2.0.41
Requires-Dist: python-dotenv==1.1.1
Requires-Dist: passlib[bcrypt]==1.7.4
Requires-Dist: python-jose[cryptography]==3.5.0
Requires-Dist: pytest==8.4.1
Requires-Dist: tomlkit==0.13.3
Requires-Dist: semver==3.0.4
Requires-Dist: qwen-agent[code_interpreter,gui,mcp,rag]
Requires-Dist: click==8.2.1
Requires-Dist: openai==1.108.1
Requires-Dist: rich==14.0.0
Requires-Dist: fastmcp==2.12.3
Requires-Dist: pydantic[email]==2.11.7
Requires-Dist: langgraph==0.6.7
Requires-Dist: langchain-openai==0.3.33
Dynamic: author
Dynamic: home-page
Dynamic: license-file
Dynamic: requires-python
